absorb/__init__.py
absorb/config/__init__.py
absorb/config/paths.py
absorb/core/__init__.py
absorb/core/idea/__init__.py
absorb/core/idea/commands.py
absorb/core/kanban/__init__.py
absorb/core/kanban/commands.py
absorb/core/tasks/__init__.py
absorb/core/tasks/commands.py
absorb/main.py
absorb/utils/idea_utils.py
absorb/utils/kanban_utils.py
absorb/utils/log_utils.py
absorb/utils/tasks_utils.py
absorb-0.1.2.dist-info/entry_points.txt
absorb-0.1.2.dist-info/LICENSE
absorb-0.1.2.dist-info/WHEEL
absorb-0.1.2.dist-info/METADATA
absorb-0.1.2.dist-info/RECORD
