Metadata-Version: 2.1
Name: absorb
Version: 0.1.2
Summary: The extensible, feature-rich CLI workspace.
Author: Aadhav Vignesh
Author-email: aadhav.n1@gmail.com
Requires-Python: >=3.7,<4.0
Classifier: Programming Language :: Python :: 3
Classifier: Programming Language :: Python :: 3.10
Classifier: Programming Language :: Python :: 3.7
Classifier: Programming Language :: Python :: 3.8
Classifier: Programming Language :: Python :: 3.9
Requires-Dist: GitPython (>=3.1.17,<4.0.0)
Requires-Dist: Pygments (>=2.9.0,<3.0.0)
Requires-Dist: click (>=8.0.1,<9.0.0)
Requires-Dist: click-plugins (>=1.1.1,<2.0.0)
Requires-Dist: colorama (>=0.4.4,<0.5.0)
Requires-Dist: commonmark (>=0.9.1,<0.10.0)
Requires-Dist: gitdb (>=4.0.7,<5.0.0)
Requires-Dist: importlib-metadata (>=4.5.0,<5.0.0)
Requires-Dist: python-json-logger (>=2.0.1,<3.0.0)
Requires-Dist: rich (>=10.3.0,<11.0.0)
Requires-Dist: setuptools (==65.5.1)
Requires-Dist: smmap (>=4.0.0,<5.0.0)
Requires-Dist: typing-extensions (>=3.10.0,<4.0.0)
Requires-Dist: zipp (>=3.4.1,<4.0.0)
